post_canonical/__init__.py
post_canonical/builder.py
post_canonical/cli.py
post_canonical/py.typed
post_canonical/visualization.py
post_canonical/core/__init__.py
post_canonical/core/alphabet.py
post_canonical/core/errors.py
post_canonical/core/pattern.py
post_canonical/core/rule.py
post_canonical/core/variable.py
post_canonical/matching/__init__.py
post_canonical/matching/binding.py
post_canonical/matching/matcher.py
post_canonical/matching/unifier.py
post_canonical/presets/__init__.py
post_canonical/presets/alphabets.py
post_canonical/presets/examples.py
post_canonical/query/__init__.py
post_canonical/query/reachability.py
post_canonical/serialization/__init__.py
post_canonical/serialization/json_codec.py
post_canonical/system/__init__.py
post_canonical/system/derivation.py
post_canonical/system/executor.py
post_canonical/system/pcs.py
post_canonical-2.0.0.dist-info/METADATA
post_canonical-2.0.0.dist-info/WHEEL
post_canonical-2.0.0.dist-info/entry_points.txt
post_canonical-2.0.0.dist-info/licenses/LICENSE
post_canonical-2.0.0.dist-info/RECORD
