Metadata-Version: 2.4
Name: post-canonical
Version: 2.0.0
Summary: Post Canonical Systems - A Python implementation of Emil Post's formal string rewriting systems
Project-URL: Repository, https://github.com/niarenaw/post-canonical
Project-URL: Documentation, https://github.com/niarenaw/post-canonical#readme
Author: Post Canonical Contributors
License-Expression: MIT
License-File: LICENSE
Classifier: Development Status :: 4 - Beta
Classifier: License :: OSI Approved :: MIT License
Classifier: Programming Language :: Python :: 3
Classifier: Programming Language :: Python :: 3.12
Classifier: Topic :: Scientific/Engineering :: Mathematics
Classifier: Typing :: Typed
Requires-Python: >=3.12
